{"_type":"export","__export_format":4,"__export_date":"2020-05-09T05:38:17.199Z","__export_source":"insomnia.desktop.app:v7.1.1","resources":[{"_id":"req_a77b9892a7904e7a8420bd6cd37c3177","authentication":{},"body":{},"created":1589002122660,"description":"","headers":[],"isPrivate":false,"metaSortKey":-1589002122660,"method":"DELETE","modified":1589002630547,"name":"Delete Transaction","parameters":[],"parentId":"wrk_f3922b2468634b1c9232a4905bc9a3db","settingDisableRenderRequestBody":false,"settingEncodeUrl":true,"settingFollowRedirects":"global","settingRebuildPath":true,"settingSendCookies":true,"settingStoreCookies":true,"url":"http://localhost:3333/transactions/:id","_type":"request"},{"_id":"wrk_f3922b2468634b1c9232a4905bc9a3db","created":1588898154269,"description":"","modified":1588898154269,"name":"Insomnia","parentId":null,"_type":"workspace"},{"_id":"req_ea36b65164ed43acb30de28311ed7eaf","authentication":{},"body":{},"created":1588996124410,"description":"","headers":[],"isPrivate":false,"metaSortKey":-1588996124410,"method":"GET","modified":1588996129209,"name":"List Transactions","parameters":[],"parentId":"wrk_f3922b2468634b1c9232a4905bc9a3db","settingDisableRenderRequestBody":false,"settingEncodeUrl":true,"settingFollowRedirects":"global","settingRebuildPath":true,"settingSendCookies":true,"settingStoreCookies":true,"url":"http://localhost:3333/transactions","_type":"request"},{"_id":"req_994878a385a2429da0db4d9dd9df0473","authentication":{},"body":{"mimeType":"application/json","text":"{\n\t\"title\": \"Moto\",\n\t\"type\": \"outcome\",\n\t\"category\":\"Gasto\",\n\t\"value\": 1400\n}"},"created":1588995910747,"description":"","headers":[{"id":"pair_bc7c9b53b55542f7b2cc74d8c77673fc","name":"Content-Type","value":"application/json"}],"isPrivate":false,"metaSortKey":-1588995910748,"method":"POST","modified":1589000109224,"name":"Create Transaction","parameters":[],"parentId":"wrk_f3922b2468634b1c9232a4905bc9a3db","settingDisableRenderRequestBody":false,"settingEncodeUrl":true,"settingFollowRedirects":"global","settingRebuildPath":true,"settingSendCookies":true,"settingStoreCookies":true,"url":"http://localhost:3333/transactions","_type":"request"},{"_id":"req_515c029b351742f183addbbd4f4eaa31","authentication":{},"body":{"mimeType":"multipart/form-data","params":[{"description":"","id":"pair_61182cb555d1493f94f1ff0b5e0ce2e0","name":"file","type":"file","value":""}]},"created":1588999944187,"description":"","headers":[{"id":"pair_5438b54de78949e9b314f4cd701c8953","name":"Content-Type","value":"multipart/form-data"}],"isPrivate":false,"metaSortKey":-1588995910698,"method":"POST","modified":1589002654637,"name":"Import Transactions","parameters":[],"parentId":"wrk_f3922b2468634b1c9232a4905bc9a3db","settingDisableRenderRequestBody":false,"settingEncodeUrl":true,"settingFollowRedirects":"global","settingRebuildPath":true,"settingSendCookies":true,"settingStoreCookies":true,"url":"http://localhost:3333/transactions/import","_type":"request"},{"_id":"env_8ab9b9db37199a394993c931bb1c5491438e2704","color":null,"created":1588898154377,"data":{},"dataPropertyOrder":null,"isPrivate":false,"metaSortKey":1588898154377,"modified":1588898154377,"name":"Base Environment","parentId":"wrk_f3922b2468634b1c9232a4905bc9a3db","_type":"environment"},{"_id":"jar_8ab9b9db37199a394993c931bb1c5491438e2704","cookies":[],"created":1588898154382,"modified":1588898154382,"name":"Default Jar","parentId":"wrk_f3922b2468634b1c9232a4905bc9a3db","_type":"cookie_jar"}]}